{"cameraMode":{"drawMode":0,"name":"Shaded","section":"Shading Mode"},"sceneLighting":true,"audioPlay":false,"sceneViewState":{"m_AlwaysRefresh":false,"showFog":true,"showSkybox":true,"showFlares":true,"showImageEffects":true,"showParticleSystems":true,"showVisualEffectGraphs":true,"m_FxEnabled":true},"in2DMode":false,"pivot":{"x":-2443.53515625,"y":18.4194393157959,"z":-226.97622680664063},"rotation":{"x":0.0046781254932284359,"y":0.9735860228538513,"z":0.0068989465944468979,"w":-0.2283543050289154},"size":0.9734504222869873,"orthographic":false}